tvl/__init__.py
tvl/backend.py
tvl/dataset.py
tvl/testing.py
tvl/transforms.py
tvl-0.1.0b18.dist-info/LICENSE
tvl-0.1.0b18.dist-info/METADATA
tvl-0.1.0b18.dist-info/WHEEL
tvl-0.1.0b18.dist-info/top_level.txt
tvl-0.1.0b18.dist-info/RECORD
