Metadata-Version: 2.1
Name: tvl
Version: 0.1.0b18
Summary: UNKNOWN
Home-page: UNKNOWN
Author: Aiden Nibali
License: Apache Software License 2.0
Platform: UNKNOWN
License-File: LICENSE
Requires-Dist: numpy
Requires-Dist: torch
Provides-Extra: fffrbackend
Requires-Dist: tvl-backends-fffr (==0.1.0b18) ; extra == 'fffrbackend'
Provides-Extra: nvdecbackend
Requires-Dist: tvl-backends-nvdec (==0.1.0b18) ; extra == 'nvdecbackend'
Provides-Extra: opencvbackend
Requires-Dist: tvl-backends-opencv (==0.1.0b18) ; extra == 'opencvbackend'
Provides-Extra: pyavbackend
Requires-Dist: tvl-backends-pyav (==0.1.0b18) ; extra == 'pyavbackend'
